astromy/__init__.py
astromy/__version__.py
astromy/astromatic.py
astromy/catalog.py
astromy/cube.py
astromy/image-old.py
astromy/image.py
astromy/line.py
astromy/mygrizli.py
astromy/spec1d.py
astromy/spec2d.py
astromy/wcs.py
astromy-0.1.2.dist-info/LICENSE
astromy-0.1.2.dist-info/METADATA
astromy-0.1.2.dist-info/WHEEL
astromy-0.1.2.dist-info/top_level.txt
astromy-0.1.2.dist-info/RECORD
